wim/__about__.py
wim/__init__.py
wim/cli.py
wim/image.py
wim-1.2.0.dist-info/METADATA
wim-1.2.0.dist-info/WHEEL
wim-1.2.0.dist-info/entry_points.txt
wim-1.2.0.dist-info/licenses/LICENSE
wim-1.2.0.dist-info/RECORD
