Metadata-Version: 2.4
Name: wim
Version: 1.2.0
Summary: wim is a command line tool to create images for the web.
Project-URL: Documentation, https://github.com/yaph/wim#readme
Project-URL: Issues, https://github.com/yaph/wim/issues
Project-URL: Source, https://github.com/yaph/wim
Author-email: Ramiro Gómez <code@ramiro.org>
License-Expression: MIT
License-File: LICENSE
Keywords: cli,command-line-tool,image,image-optimization,image-processing,python-package
Requires-Python: >=3.10
Requires-Dist: pillow
